{
  "$schema": "https://raw.githubusercontent.com/spdx/spdx-spec/v2.2.1/schemas/spdx-schema.json",
  "spdxVersion": "SPDX-2.2",
  "dataLicense": "CC0-1.0",
  "SPDXID": "SPDXRef-DOCUMENT",
  "documentNamespace": "https://spdx.org/spdxdocs/boost-variant2-x64-linux-1.89.0-e4e6f25e-f11d-4aaf-a27b-f9fa910af2b7",
  "name": "boost-variant2:x64-linux@1.89.0 9d41e844654b982843f0bdf76cee0dd272deea315138143b7fccb36d3163d400",
  "creationInfo": {
    "creators": [
      "Tool: vcpkg-2025-07-21-1.fc42"
    ],
    "created": "2025-10-07T02:40:33Z"
  },
  "relationships": [
    {
      "spdxElementId": "SPDXRef-port",
      "relationshipType": "GENERATES",
      "relatedSpdxElement": "SPDXRef-binary"
    },
    {
      "spdxElementId": "SPDXRef-port",
      "relationshipType": "CONTAINS",
      "relatedSpdxElement": "SPDXRef-file-0"
    },
    {
      "spdxElementId": "SPDXRef-port",
      "relationshipType": "CONTAINS",
      "relatedSpdxElement": "SPDXRef-file-1"
    },
    {
      "spdxElementId": "SPDXRef-binary",
      "relationshipType": "GENERATED_FROM",
      "relatedSpdxElement": "SPDXRef-port"
    },
    {
      "spdxElementId": "SPDXRef-file-0",
      "relationshipType": "CONTAINED_BY",
      "relatedSpdxElement": "SPDXRef-port"
    },
    {
      "spdxElementId": "SPDXRef-file-0",
      "relationshipType": "DEPENDENCY_MANIFEST_OF",
      "relatedSpdxElement": "SPDXRef-port"
    },
    {
      "spdxElementId": "SPDXRef-file-1",
      "relationshipType": "CONTAINED_BY",
      "relatedSpdxElement": "SPDXRef-port"
    }
  ],
  "packages": [
    {
      "name": "boost-variant2",
      "SPDXID": "SPDXRef-port",
      "versionInfo": "1.89.0",
      "downloadLocation": "git+https://github.com/Microsoft/vcpkg#ports/boost-variant2",
      "homepage": "https://www.boost.org/libs/variant2",
      "licenseConcluded": "BSL-1.0",
      "licenseDeclared": "NOASSERTION",
      "copyrightText": "NOASSERTION",
      "description": "Boost variant2 module",
      "comment": "This is the port (recipe) consumed by vcpkg."
    },
    {
      "name": "boost-variant2:x64-linux",
      "SPDXID": "SPDXRef-binary",
      "versionInfo": "9d41e844654b982843f0bdf76cee0dd272deea315138143b7fccb36d3163d400",
      "downloadLocation": "NONE",
      "licenseConcluded": "BSL-1.0",
      "licenseDeclared": "NOASSERTION",
      "copyrightText": "NOASSERTION",
      "comment": "This is a binary package built by vcpkg."
    },
    {
      "SPDXID": "SPDXRef-resource-0",
      "name": "boostorg/variant2",
      "downloadLocation": "git+https://github.com/boostorg/variant2@boost-1.89.0",
      "licenseConcluded": "NOASSERTION",
      "licenseDeclared": "NOASSERTION",
      "copyrightText": "NOASSERTION",
      "checksums": [
        {
          "algorithm": "SHA512",
          "checksumValue": "1adbf2e53eeace2b66790afbb099b117355605da8b074554c47e70ae755e273fd343d90002bbc2d5e20f32b0bfb43773cc5e0e31b3a31623846baa051d2eb4a7"
        }
      ]
    }
  ],
  "files": [
    {
      "fileName": "./vcpkg.json",
      "SPDXID": "SPDXRef-file-0",
      "checksums": [
        {
          "algorithm": "SHA256",
          "checksumValue": "153542d5f79e64e82ebe788c3fda9affe21dcb302636143097e0daea519b013c"
        }
      ],
      "licenseConcluded": "NOASSERTION",
      "copyrightText": "NOASSERTION"
    },
    {
      "fileName": "./portfile.cmake",
      "SPDXID": "SPDXRef-file-1",
      "checksums": [
        {
          "algorithm": "SHA256",
          "checksumValue": "4db43060881541fec6d4ecb3370cc6b38af1a610ff825878b66933a041014df0"
        }
      ],
      "licenseConcluded": "NOASSERTION",
      "copyrightText": "NOASSERTION"
    }
  ]
}
